antsibull_nox/__init__.py
antsibull_nox/_pydantic.py
antsibull_nox/ansible.py
antsibull_nox/ansible_test_config.py
antsibull_nox/cd.py
antsibull_nox/cli.py
antsibull_nox/config.py
antsibull_nox/container.py
antsibull_nox/data_util.py
antsibull_nox/ee_config.py
antsibull_nox/init.py
antsibull_nox/interpret_config.py
antsibull_nox/lint_config.py
antsibull_nox/py.typed
antsibull_nox/utils.py
antsibull_nox/collection/__init__.py
antsibull_nox/collection/build.py
antsibull_nox/collection/data.py
antsibull_nox/collection/extract.py
antsibull_nox/collection/install.py
antsibull_nox/collection/search.py
antsibull_nox/collection/utils.py
antsibull_nox/data/action-groups.py
antsibull_nox/data/antsibull-nox-lint-config.py
antsibull_nox/data/antsibull_nox_data_util.py
antsibull_nox/data/avoid-characters.py
antsibull_nox/data/file-yamllint.py
antsibull_nox/data/get-package-versions.py
antsibull_nox/data/license-check.py
antsibull_nox/data/license-check.py.license
antsibull_nox/data/no-trailing-whitespace.py
antsibull_nox/data/no-unwanted-files.py
antsibull_nox/data/plugin-yamllint.py
antsibull_nox/data/rst-extra.py
antsibull_nox/data/rst-yamllint.py
antsibull_nox/messages/__init__.py
antsibull_nox/messages/parse.py
antsibull_nox/messages/utils.py
antsibull_nox/paths/__init__.py
antsibull_nox/paths/match.py
antsibull_nox/paths/utils.py
antsibull_nox/python/__init__.py
antsibull_nox/python/imports.py
antsibull_nox/python/python_dependencies.py
antsibull_nox/python/versions.py
antsibull_nox/sessions/__init__.py
antsibull_nox/sessions/ansible_lint.py
antsibull_nox/sessions/ansible_test.py
antsibull_nox/sessions/build_import_check.py
antsibull_nox/sessions/collections.py
antsibull_nox/sessions/docs_check.py
antsibull_nox/sessions/ee_check.py
antsibull_nox/sessions/extra_checks.py
antsibull_nox/sessions/license_check.py
antsibull_nox/sessions/lint.py
antsibull_nox/sessions/matrix_generator.py
antsibull_nox/sessions/utils/__init__.py
antsibull_nox/sessions/utils/output.py
antsibull_nox-1.5.0.dist-info/METADATA
antsibull_nox-1.5.0.dist-info/WHEEL
antsibull_nox-1.5.0.dist-info/entry_points.txt
antsibull_nox-1.5.0.dist-info/licenses/LICENSES/GPL-3.0-or-later.txt
antsibull_nox-1.5.0.dist-info/RECORD
