Metadata-Version: 2.4
Name: antsibull-nox
Version: 1.5.0
Summary: Changelog tool for Ansible-core and Ansible collections
Project-URL: Documentation, https://ansible.readthedocs.io/projects/antsibull-nox/
Project-URL: Source code, https://github.com/ansible-community/antsibull-nox/
Project-URL: Code of Conduct, https://docs.ansible.com/ansible/latest/community/code_of_conduct.html
Project-URL: Bug tracker, https://github.com/ansible-community/antsibull-nox/issues
Project-URL: Changelog, https://github.com/ansible-community/antsibull-nox/tree/main/CHANGELOG.md
Author-email: Felix Fontein <felix@fontein.de>, Toshio Kuratomi <a.badger@gmail.com>, Matt Clay <matt@mystile.com>
Maintainer-email: Felix Fontein <felix@fontein.de>, Maxwell G <maxwell@gtmx.me>
License-Expression: GPL-3.0-or-later
License-File: LICENSES/GPL-3.0-or-later.txt
Classifier: Development Status :: 5 - Production/Stable
Classifier: Framework :: Ansible
Classifier: Intended Audience :: Developers
Classifier: Programming Language :: Python :: 3
Classifier: Programming Language :: Python :: 3.9
Classifier: Programming Language :: Python :: 3.10
Classifier: Programming Language :: Python :: 3.11
Classifier: Programming Language :: Python :: 3.12
Classifier: Programming Language :: Python :: 3.13
Classifier: Programming Language :: Python :: 3.14
Classifier: Typing :: Typed
Requires-Python: >=3.9.0
Requires-Dist: antsibull-fileutils<2.0.0,>=1.5.0
Requires-Dist: nox>=2025.2.9
Requires-Dist: packaging
Requires-Dist: pydantic~=2.0
Requires-Dist: pyyaml
Requires-Dist: semantic-version
Requires-Dist: tomli; python_version < '3.11'
Provides-Extra: codeqa
Requires-Dist: antsibull-changelog; extra == 'codeqa'
Requires-Dist: flake8>=3.8.0; extra == 'codeqa'
Requires-Dist: pylint; extra == 'codeqa'
Requires-Dist: reuse; extra == 'codeqa'
Provides-Extra: coverage
Requires-Dist: coverage[toml]; extra == 'coverage'
Provides-Extra: dev
Requires-Dist: antsibull-changelog; extra == 'dev'
Requires-Dist: antsibull-docutils>=1.2.0; extra == 'dev'
Requires-Dist: black>=24; extra == 'dev'
Requires-Dist: coverage[toml]; extra == 'dev'
Requires-Dist: flake8>=3.8.0; extra == 'dev'
Requires-Dist: isort; extra == 'dev'
Requires-Dist: mypy; extra == 'dev'
Requires-Dist: nox; extra == 'dev'
Requires-Dist: pylint; extra == 'dev'
Requires-Dist: pytest; extra == 'dev'
Requires-Dist: pytest-cov; extra == 'dev'
Requires-Dist: pytest-error-for-skips; extra == 'dev'
Requires-Dist: reuse; extra == 'dev'
Requires-Dist: types-docutils; extra == 'dev'
Requires-Dist: types-pyyaml; extra == 'dev'
Provides-Extra: formatters
Requires-Dist: black>=24; extra == 'formatters'
Requires-Dist: isort; extra == 'formatters'
Provides-Extra: test
Requires-Dist: pytest; extra == 'test'
Requires-Dist: pytest-cov; extra == 'test'
Requires-Dist: pytest-error-for-skips; extra == 'test'
Provides-Extra: typing
Requires-Dist: antsibull-docutils>=1.2.0; extra == 'typing'
Requires-Dist: mypy; extra == 'typing'
Requires-Dist: types-docutils; extra == 'typing'
Requires-Dist: types-pyyaml; extra == 'typing'
